{
  "cipher": "ascon",
  "round": 5,
  "models": {
    "logistic": {
      "cipher": "ascon",
      "model": "logistic",
      "rounds": 5,
      "bitwise_accuracy": 0.51571875,
      "hamming_distance": 30.994,
      "word_accuracy": 0.0,
      "block_bits": 64,
      "train_time_s": 5.33
    },
    "mlp": {
      "cipher": "ascon",
      "model": "mlp",
      "rounds": 5,
      "bitwise_accuracy": 0.514109375,
      "hamming_distance": 31.097,
      "block_bits": 64,
      "train_time_s": 17.91
    },
    "cnn": {
      "cipher": "ascon",
      "model": "cnn",
      "rounds": 5,
      "bitwise_accuracy": 0.5004409171075838,
      "hamming_distance": 31.97178130511464,
      "block_bits": 64,
      "train_time_s": 4.51
    },
    "mine": {
      "cipher": "ascon",
      "model": "mine",
      "rounds": 5,
      "bitwise_accuracy": 0.5161210317460317,
      "hamming_distance": 30.96825396825397,
      "block_bits": 64,
      "train_time_s": 1.14
    },
    "random_forest": {
      "cipher": "ascon",
      "model": "random_forest",
      "rounds": 5,
      "bitwise_accuracy": 0.5139853395061729,
      "hamming_distance": 31.104938271604937,
      "block_bits": 64,
      "train_time_s": 3.08
    }
  }
}